zhinst/core/__init__.py
zhinst/core/__init__.pyi
zhinst/core/_core.pyd
zhinst/core/py.typed
zhinst/core/_tracing/__init__.pyi
zhinst/core/errors/__init__.pyi
zhinst/ziPython/__init__.py
zhinst/ziPython/py.typed
zhinst/ziPython/errors/__init__.py
zhinst_core-25.10.1.4.dist-info/METADATA
zhinst_core-25.10.1.4.dist-info/WHEEL
zhinst_core-25.10.1.4.dist-info/licenses/LICENSE.txt
zhinst_core-25.10.1.4.dist-info/RECORD
